[
   {
      "roster":{
         "id":2,
         "first":"Player",
         "last":"2",
         "position":"",
         "non_player":false,
         "gender":"",
         "is_manager":false,
         "is_owner":false,
         "thumbnail_picture_url":"/thumb_pics/thumb/missing.png",
         "full_picture_url":"/full_pics/thumb/missing.png",
         "user_id":2,
         "league_controlled":false,
         "invitation_declined":false,
         "invited":true,
         "number":null,
         "birthdate":null,
         "custom_data":[
         ],
         "league_custom_data":[
         ],
         "roster_email_addresses":[
            {
               "id":2,
               "label":"",
               "email":"player2@example.com",
               "receive_team_emails":true,
               "hide":false
            }
         ],
         "roster_telephone_numbers":[
         ],
         "address":{
            "address":"",
            "address2":null,
            "city":"",
            "state":"",
            "zip":"",
            "country":null
         },
      "contacts": [
        {
          "id": 1,
          "roster_id": 1,
          "label": "Mother",
          "first": "Jane",
          "last": "Doe",
          "user_id": null,
          "position": null,
          "contact_email_addresses": [
            {
              "id": 1,
              "label": "Parent 1",
              "email": "mom@example.com",
              "receive_team_emails": false,
              "hide": false
            }
          ],
          "contact_telephone_numbers": [
            {
              "id": 1,
              "label": "work",
              "phone_number": "555-123-4567",
              "preferred": false,
              "enable_sms": false,
              "sms_carrier": "",
              "hide": false
            },
            {
              "id": 1,
              "label": "cell",
              "phone_number": "555-234-5678",
              "preferred": false,
              "enable_sms": true,
              "sms_carrier": "at&t",
              "hide": false
            }
          ],
          "address": { "address": "", "address2": null, "city": "", "state": "", "zip": "", "country": null }
        },
        {
          "id": 1,
          "roster_id": 1,
          "label": "Father",
          "first": "John ",
          "last": "Doe",
          "user_id": 1,
          "position": null,
          "contact_email_addresses": [
            {
              "id": 1,
              "label": "Parent 2",
              "email": "dad@example.com",
              "receive_team_emails": true,
              "hide": false
            }
          ],
          "contact_telephone_numbers": [
            {
              "id": 1,
              "label": "work",
              "phone_number": "555-345-6789",
              "preferred": false,
              "enable_sms": false,
              "sms_carrier": "",
              "hide": false
            },
            {
              "id": 1,
              "label": "cell",
              "phone_number": "555-456-7890",
              "preferred": false,
              "enable_sms": true,
              "sms_carrier": "at&t",
              "hide": false
            }
          ],
          "address": { "address": "", "address2": null, "city": "", "state": "", "zip": "", "country": null }
        }
      ]
      }
   },
   {
      "roster":{
         "id":1,
         "first":"Player",
         "last":"1",
         "position":"",
         "non_player":false,
         "gender":"",
         "is_manager":true,
         "is_owner":true,
         "thumbnail_picture_url":"/thumb_pics/thumb/missing.png",
         "full_picture_url":"/full_pics/thumb/missing.png",
         "user_id":1,
         "league_controlled":false,
         "invitation_declined":false,
         "invited":true,
         "number":null,
         "birthdate":null,
         "custom_data":[

         ],
         "league_custom_data":[
         ],
         "roster_email_addresses":[
            {
               "id":1,
               "label":"Email",
               "email":"player1@teamsnap.com",
               "receive_team_emails":true,
               "hide":false
            }
         ],
         "roster_telephone_numbers":[
            {
               "id":1,
               "label":"Mobile",
               "phone_number":"5555555555",
               "preferred":false,
               "enable_sms":true,
               "sms_carrier":"at\u0026t",
               "hide":false
            }
         ],
         "address":{
            "address":"",
            "address2":null,
            "city":"",
            "state":"",
            "zip":"",
            "country":null
         },
         "contacts":[
         ]
      }
   }
]
